{
  "汉吐司": "游戏被你们镐蜂辣！！！🌶️🌶️🌶️",
  "[BIG SHOT]": "I love you [doge]",
  "古镇天Gugle": "电量量可爱",
  "匿名_0x01": "加油，希望你们能继续坚持下去！",
  "KFACBT": "加油！",
  "laohutongzhi": "加油",
  "EnderMoxynz": "qwqwqwqwqwqwqwqwqwqwqwq",
  "姜胤": "祝梗体中文越来越好！\ndl.meme.teahou.se yyds!",
  "羽末": "喵",
  "YuChuXi": "梗体中文给了我和我的伙伴们许多快乐",
  "DaJiFick": "Never Gonna Give You Up(",
  "Xzavier0707": "十分喜欢里面更改的终末之诗，感谢！",
  "1amSherluck": "加油！",
  "Moments_Closed_Switch": "你做的好，你做得好啊（无慈悲）",
  "匿名_0x02": "三杯咖啡请收好～",
  "ForeverMIAO": "加油！！永远热爱！！",
  "天下大帅比": "力量虽然很薄弱，但是还能希望梗体中文的制作组越来越好",
  "DoroWolf": "多洛超可爱同人gkd",
  "孤123丫": "加油！💪希望越做越好",
  "章夜辰": "加油",
  "NBDK": "加油",
  "匿名_0x03": "一直以来辛苦了，这个年头活着不容易，希望所有用爱发电的人能获得幸福、快乐",
  "MNW小石头": "加油，挺过去",
  "LaoT": "Never gonna give you up~~~（莫名被骗）",
  "匿名_0x04": "加油(ง •_•)ง",
  "匿名_0x05": "忒牛了呀，加油，希望以后更牛啤",
  "winver1234_": "我宣布个事！",
  "匿名_0x06": "都挺不容易的……",
  "CallumBTW_": "可爱捏",
  "AntiRain15": "一个令人快乐的资源包",
  "匿名_0x07": "加油哦",
  "小刚嘿": "梗体中文真的很生草！！!"
}
